energy_counters/__init__.py
energy_counters/carlo_gavazzi/__init__.py
energy_counters/carlo_gavazzi/em530.py
energy_counters/common/__init__.py
energy_counters/common/configurations.py
energy_counters/contrel/__init__.py
energy_counters/contrel/ud3h.py
energy_counters/diris/__init__.py
energy_counters/diris/a10.py
energy_counters/lovato/__init__.py
energy_counters/lovato/dmg1.py
energy_counters/lovato/dmg210.py
energy_counters/lovato/dmg6.py
energy_counters/lovato/dmg800.py
energy_counters/redz/__init__.py
energy_counters/redz/lkm144.py
energy_counters/schneider/__init__.py
energy_counters/schneider/iem3155.py
energy_counters/schneider/iem3250.py
energy_counters/schneider/iem3255.py
energy_counters-1.3.0.dist-info/licenses/LICENSE
energy_counters-1.3.0.dist-info/METADATA
energy_counters-1.3.0.dist-info/WHEEL
energy_counters-1.3.0.dist-info/top_level.txt
energy_counters-1.3.0.dist-info/RECORD
