Metadata-Version: 2.4
Name: energy-counters
Version: 1.3.0
Summary: A Python library for reading data from various electrical energy counters including Carlo Gavazzi, Contrel, Diris, Lovato, RedZ, and Schneider devices
Author-email: nobrega8 <afonsognobrega@gmail.com>
License-Expression: MIT
Project-URL: Homepage, https://github.com/nobrega8/energy-counters
Project-URL: Bug Tracker, https://github.com/nobrega8/energy-counters/issues
Keywords: energy,modbus,counters,carlo gavazzi,electrical,lovato,schneider,python
Classifier: Development Status :: 4 - Beta
Classifier: Intended Audience :: Developers
Classifier: Topic :: Software Development :: Libraries :: Python Modules
Classifier: Topic :: System :: Hardware
Classifier: Programming Language :: Python :: 3
Classifier: Programming Language :: Python :: 3.8
Classifier: Programming Language :: Python :: 3.9
Classifier: Programming Language :: Python :: 3.10
Classifier: Programming Language :: Python :: 3.11
Classifier: Programming Language :: Python :: 3.12
Requires-Python: >=3.8
License-File: LICENSE
Requires-Dist: pyserial
Requires-Dist: pymodbus
Dynamic: license-file
